hpo_toolkit-0.7.0.dist-info/licenses/LICENSE
hpotk/__init__.py
hpotk/py.typed
hpotk/algorithm/__init__.py
hpotk/algorithm/_augment.py
hpotk/algorithm/_traversal.py
hpotk/algorithm/similarity/__init__.py
hpotk/algorithm/similarity/_ic.py
hpotk/algorithm/similarity/_model.py
hpotk/algorithm/similarity/_resnik.py
hpotk/annotations/__init__.py
hpotk/annotations/_api.py
hpotk/annotations/_base.py
hpotk/annotations/_simple.py
hpotk/annotations/_test__base.py
hpotk/annotations/_test__simple.py
hpotk/annotations/load/__init__.py
hpotk/annotations/load/_api.py
hpotk/annotations/load/hpoa/__init__.py
hpotk/annotations/load/hpoa/_impl.py
hpotk/annotations/load/hpoa/_test__impl.py
hpotk/constants/__init__.py
hpotk/constants/hpo/__init__.py
hpotk/constants/hpo/base.py
hpotk/constants/hpo/frequency.py
hpotk/constants/hpo/inheritance.py
hpotk/constants/hpo/onset.py
hpotk/constants/hpo/organ_system.py
hpotk/constants/hpo/severity.py
hpotk/graph/__init__.py
hpotk/graph/_api.py
hpotk/graph/_csr_graph.py
hpotk/graph/_csr_idx_graph.py
hpotk/graph/_factory.py
hpotk/graph/_test__api.py
hpotk/graph/_test__csr_graph.py
hpotk/graph/_test__factory.py
hpotk/graph/_test_csr_idx_graph.py
hpotk/graph/_test_data.py
hpotk/graph/csr/__init__.py
hpotk/graph/csr/_csr.py
hpotk/graph/csr/_test__csr.py
hpotk/model/__init__.py
hpotk/model/_base.py
hpotk/model/_term.py
hpotk/model/_term_id.py
hpotk/model/_test__term_id.py
hpotk/ontology/__init__.py
hpotk/ontology/_api.py
hpotk/ontology/_default.py
hpotk/ontology/load/__init__.py
hpotk/ontology/load/obographs/__init__.py
hpotk/ontology/load/obographs/_factory.py
hpotk/ontology/load/obographs/_load.py
hpotk/ontology/load/obographs/_model.py
hpotk/ontology/load/obographs/_test_load.py
hpotk/store/__init__.py
hpotk/store/_api.py
hpotk/store/_config.py
hpotk/store/_github.py
hpotk/util/__init__.py
hpotk/util/_extract.py
hpotk/util/_io.py
hpotk/util/_log.py
hpotk/util/_validate.py
hpotk/util/sort/__init__.py
hpotk/util/sort/_api.py
hpotk/util/sort/_hierarchical.py
hpotk/util/sort/_test__hierarchical.py
hpo_toolkit-0.7.0.dist-info/METADATA
hpo_toolkit-0.7.0.dist-info/WHEEL
hpo_toolkit-0.7.0.dist-info/top_level.txt
hpo_toolkit-0.7.0.dist-info/RECORD
