Metadata-Version: 2.4
Name: hpo-toolkit
Version: 0.7.0
Summary: A toolkit for working with Human Phenotype Ontology in Python
Author-email: Daniel Danis <daniel.gordon.danis@protonmail.com>
License:                     GNU GENERAL PUBLIC LICENSE
Project-URL: homepage, https://github.com/ielis/hpo-toolkit
Project-URL: repository, https://github.com/ielis/hpo-toolkit.git
Project-URL: documentation, https://ielis.github.io/hpo-toolkit/stable
Project-URL: bugtracker, https://github.com/ielis/hpo-toolkit/issues
Keywords: human phenotype ontology,HPO,library
Classifier: Development Status :: 3 - Alpha
Classifier: Operating System :: OS Independent
Classifier: Programming Language :: Python :: 3.9
Classifier: Programming Language :: Python :: 3.10
Classifier: Programming Language :: Python :: 3.11
Classifier: Programming Language :: Python :: 3.12
Classifier: Programming Language :: Python :: 3.13
Requires-Python: >=3.9
License-File: LICENSE
Requires-Dist: numpy>=1.23
Requires-Dist: certifi
Provides-Extra: test
Requires-Dist: pytest<9.0.0,>=8.0.0; extra == "test"
Requires-Dist: ddt>=1.6.0; extra == "test"
Requires-Dist: ruff==0.12.2; extra == "test"
Provides-Extra: docs
Requires-Dist: sphinx>=7.0.0; extra == "docs"
Requires-Dist: sphinx-copybutton>=0.5.0; extra == "docs"
Requires-Dist: sphinx-rtd-theme>=1.3.0; extra == "docs"
Provides-Extra: bench
Requires-Dist: pandas<3.0,>=1.0.0; extra == "bench"
Dynamic: license-file
